{
  "data_asset_type": null,
  "expectation_suite_name": "expectation-store-sales",
  "expectations": [
    {
      "expectation_type": "expect_column_values_to_be_unique",
      "kwargs": {
        "column": "invoice_id"
      },
      "meta": {}
    },
    {
      "expectation_type": "expect_column_values_to_be_between",
      "kwargs": {
        "column": "rating",
        "max_value": 10,
        "min_value": 0
      },
      "meta": {}
    },
    {
      "expectation_type": "expect_column_values_to_be_in_set",
      "kwargs": {
        "column": "product_line",
        "value_set": [
          "Health and beauty",
          "Electronic accessories",
          "Home and lifestyle",
          "Sports and travel",
          "Food and beverages",
          "Fashion accessories"
        ]
      },
      "meta": {}
    },
    {
      "expectation_type": "expect_column_values_to_be_in_type_list",
      "kwargs": {
        "column": "unit_price",
        "type_list": [
          "int64",
          "float64"
        ]
      },
      "meta": {}
    },
    {
      "expectation_type": "expect_table_column_count_to_equal",
      "kwargs": {
        "value": 17
      },
      "meta": {}
    },
    {
      "expectation_type": "expect_column_to_exist",
      "kwargs": {
        "column": "total"
      },
      "meta": {}
    },
    {
      "expectation_type": "expect_table_row_count_to_equal",
      "kwargs": {
        "value": 1000
      },
      "meta": {}
    },
    {
      "expectation_type": "expect_column_mean_to_be_between",
      "kwargs": {
        "column": "gross_income",
        "max_value": 49.65,
        "min_value": 0.51
      },
      "meta": {}
    }
  ],
  "ge_cloud_id": null,
  "meta": {
    "great_expectations_version": "0.18.19"
  }
}